PygameWait/__init__.py
pygamewait-1.0.3.dist-info/licenses/LICENSE
pygamewait-1.0.3.dist-info/METADATA
pygamewait-1.0.3.dist-info/WHEEL
pygamewait-1.0.3.dist-info/top_level.txt
pygamewait-1.0.3.dist-info/RECORD
