Metadata-Version: 2.4
Name: PygameWait
Version: 1.0.3
Summary: Waits but dont get in the way of closing the pygame window
Author-email: xBlake_2012x <Blake_Brent@outlook.com>
License: MIT License
Classifier: License :: OSI Approved :: MIT License
Classifier: Programming Language :: Python :: 3
Requires-Python: >=3.6
License-File: LICENSE
Dynamic: license-file
